pyconfig/__init__.py
pyconfig/__version__.py
pydevconf/__init__.py
pydevconf/__version__.py
python_config/__init__.py
python_config/__version__.py
pydevconf-1.0.2.dist-info/LICENSE
pydevconf-1.0.2.dist-info/METADATA
pydevconf-1.0.2.dist-info/WHEEL
pydevconf-1.0.2.dist-info/top_level.txt
pydevconf-1.0.2.dist-info/RECORD
