Metadata-Version: 2.1
Name: pydevconf
Version: 1.0.2
Summary: Library to get information identical to python-config
Home-page: https://github.com/ktnyt/PythonConfig
Author: Kotone Itaya
Author-email: kotone@sfc.keio.ac.jp
License: MIT
Platform: UNKNOWN
Classifier: License :: OSI Approved :: MIT License
Classifier: Programming Language :: Python
Classifier: Programming Language :: Python :: 3
Classifier: Programming Language :: Python :: 3.6
Classifier: Programming Language :: Python :: Implementation :: CPython
Classifier: Programming Language :: Python :: Implementation :: PyPy
Requires-Python: >=3.6.0
